bisque-0.3.0.dist-info/METADATA
bisque-0.3.0.dist-info/WHEEL
bisque-0.3.0.dist-info/licenses/LICENSE.txt
bisque/.pytest_cache/.gitignore
bisque/.pytest_cache/CACHEDIR.TAG
bisque/.pytest_cache/README.md
bisque/.pytest_cache/v/cache/lastfailed
bisque/.pytest_cache/v/cache/nodeids
bisque/.pytest_cache/v/cache/stepwise
bisque/__init__.py
bisque/builder/__init__.py
bisque/builder/_html5lib/__init__.py
bisque/builder/_html5lib/attrs.py
bisque/builder/_html5lib/element_and_text.py
bisque/builder/_html5lib/html5_support.py
bisque/builder/_html5lib/main.py
bisque/builder/_htmlparser/__init__.py
bisque/builder/_htmlparser/builder.py
bisque/builder/_htmlparser/parser.py
bisque/builder/_lxml/__init__.py
bisque/builder/_lxml/html_builder.py
bisque/builder/_lxml/util.py
bisque/builder/_lxml/xml_builder.py
bisque/builder/core/__init__.py
bisque/builder/core/features.py
bisque/builder/core/html_builder.py
bisque/builder/core/main.py
bisque/builder/core/parser_names.py
bisque/builder/core/registry.py
bisque/builder/core/sax_builder.py
bisque/builder/core/xml.py
bisque/css.py
bisque/dammit/__init__.py
bisque/dammit/dependency_resolution.py
bisque/dammit/detection.py
bisque/dammit/encodings.py
bisque/dammit/substitution.py
bisque/diagnose.py
bisque/element/.pytest_cache/.gitignore
bisque/element/.pytest_cache/CACHEDIR.TAG
bisque/element/.pytest_cache/README.md
bisque/element/.pytest_cache/v/cache/nodeids
bisque/element/.pytest_cache/v/cache/stepwise
bisque/element/__init__.py
bisque/element/attributes.py
bisque/element/encodings.py
bisque/element/sentinels.py
bisque/element/tag_core/__init__.py
bisque/element/tag_core/main.py
bisque/element/tag_core/page_element.py
bisque/element/tag_core/results.py
bisque/element/tag_core/soup_strainer.py
bisque/element/tag_core/string_types/__init__.py
bisque/element/tag_core/string_types/doc.py
bisque/element/tag_core/string_types/navigable.py
bisque/element/tag_core/string_types/preformatted.py
bisque/element/tag_core/tag.py
bisque/element/whitespace.py
bisque/formatter.py
bisque/main.py
bisque/models.py
bisque/tests/.pytest_cache/.gitignore
bisque-0.3.0.dist-info/RECORD
